digitmap/__init__.py
digitmap/_matcher.py
digitmap/_parser.py
digitmap/_translator.py
digitmap/digitmap.lark
digitmap/model.py
digitmap-1.0.0.dist-info/LICENSE.md
digitmap-1.0.0.dist-info/WHEEL
digitmap-1.0.0.dist-info/METADATA
digitmap-1.0.0.dist-info/RECORD
