Metadata-Version: 2.1
Name: digitmap
Version: 1.0.0
Summary: Package for working with digit maps - a syntax for indicating the sequence of digits that define a valid and complete dialing attempt by a VoIP telephone user.
Home-page: https://github.com/gdereese/digitmap
License: MIT
Keywords: digit-map,parser,telephony,voip
Author: Gary DeReese
Author-email: garydereese@sbcglobal.net
Requires-Python: >=3.8,<4.0
Classifier: License :: OSI Approved :: MIT License
Classifier: Programming Language :: Python :: 3
Classifier: Programming Language :: Python :: 3.8
Classifier: Programming Language :: Python :: 3.9
Requires-Dist: lark (>=0.11.3,<0.12.0)
Project-URL: Issues, https://github.com/gdereese/digitmap/issues
Project-URL: Repository, https://github.com/gdereese/digitmap
